{
  "headers": {
    "access-control-allow-origin": "*",
    "set-cookie": "__cfduid=df30b87cb5d570cafc3da4d1ce1876e291604160764; expires=Mon, 30-Nov-20 16:12:44 GMT; path=/; domain=.deno.land; HttpOnly; SameSite=Lax; Secure",
    "vary": "Accept-Encoding",
    "x-amz-id-2": "SJygsfwka9J74dBayzmUlL6cMtgJ9FTKlAcguqC8TmqGUJkmwLxi7+jtTwbfavC/zXJHkmOOZpI=",
    "date": "Sat, 31 Oct 2020 16:12:44 GMT",
    "accept-ranges": "bytes",
    "etag": "\"41197446e5b651020a5f382d3f46c0b7\"",
    "cf-request-id": "062107d2760000180308364000000001",
    "x-amz-request-id": "7AB8B55743BEB0BF",
    "x-amz-version-id": "WC3gkBuGBgD2vVDWI822CqZAAgLevg1U",
    "report-to": "{\"endpoints\":[{\"url\":\"https:\\/\\/a.nel.cloudflare.com\\/report?s=JC7XPfmNXcBfQ%2By1fvlWSj9h5yEbeZS8ENhKTCDrd3l%2F5BH%2Fsi8OXPUvV0N6HDpcr8YyOAYJ084De48jQA%2FYBcC6en80Ke72Qmg%3D\"}],\"group\":\"cf-nel\",\"max_age\":604800}",
    "server": "cloudflare",
    "content-length": "717",
    "cf-cache-status": "HIT",
    "age": "419625",
    "expect-ct": "max-age=604800, report-uri=\"https://report-uri.cloudflare.com/cdn-cgi/beacon/expect-ct\"",
    "cf-ray": "5eaea8ca5b401803-ATL",
    "cache-control": "public, max-age=31536000, immutable",
    "content-type": "application/typescript; charset=utf-8",
    "last-modified": "Sat, 03 Oct 2020 12:59:09 GMT",
    "nel": "{\"report_to\":\"cf-nel\",\"max_age\":604800}"
  },
  "url": "https://deno.land/std@0.73.0/path/mod.ts"
}